arcpylogger/__init__.py
arcpylogger/arcpylogger.py
arcpylogger/arcpyloggerhelper.py
arcpylogger-2.1.0.dist-info/DESCRIPTION.rst
arcpylogger-2.1.0.dist-info/METADATA
arcpylogger-2.1.0.dist-info/RECORD
arcpylogger-2.1.0.dist-info/WHEEL
arcpylogger-2.1.0.dist-info/metadata.json
arcpylogger-2.1.0.dist-info/top_level.txt
