Metadata-Version: 2.0
Name: arcpylogger
Version: 2.1.0
Summary: Classes to define ArcPy message stream handlers and a helper function for us noobs.
Home-page: https://github.com/gisinc/ArcPyLogger
Author: cfricke, carnold
Author-email: cfricke@gisinc.com, carnold@gisinc.com
License: MIT
Platform: UNKNOWN
